[
  {
    "name": "2024",
    "classes": [
      ["Englishd", "ff08"],
      ["Freea", "f008"],
      ["Physicsa", "0ff8"],
      ["Freeb", "f0f8"],
      ["MathsMethodsa", "0008"],
      ["SoftwareDeva", "00f8"]
    ],
    "rows": [
      [
        "Day",
        "Period 1",
        "Period 2",
        "Period 3",
        "Period 4",
        "Period 5",
        "Period 6"
      ],
      ["1", 0, 0, 1, 1, 2, 2],
      ["2", 3, 4, 2, 0, 5, 1],
      ["3", 4, 4, 5, 5, 3, 3],
      ["4", 1, 1, 2, 2, 0, 0],
      ["5", 3, 3, 5, 5, 4, 4]
    ],
    "widths": [
      [7, 7, 7, 7, 7, 7, 7],
      [7, 7, 7, 7, 7, 7, 7],
      [7, 7, 7, 7, 7, 7, 7],
      [7, 7, 7, 7, 7, 7, 7],
      [7, 7, 7, 7, 7, 7, 7],
      [7, 7, 7, 7, 7, 7, 7]
    ]
  },
  {
    "name": "2023",
    "classes": [
      ["Freea", "f008"],
      ["Englishd", "ff08"],
      ["Physicsa", "0ff8"],
      ["Freeb", "f0f8"],
      ["SoftwareDeva", "00f8"],
      ["MathsMethodsa", "0008"]
    ],
    "rows": [
      [
        "Week A",
        "Period 1",
        "Period 2",
        "Period 3",
        "Period 4",
        "Period 5",
        "Period 6"
      ],
      ["1", 0, 0, 1, 1, 2, 2],
      ["2", 3, 4, 2, 0, 5, 1],
      ["3", 4, 4, 3, 3],
      ["4", 2, 2, 0, 0, 1, 5],
      ["5", 3, 3, 5, 5, 4, 4],
      [
        "Week B",
        "Period 1",
        "Period 2",
        "Period 3",
        "Period 4",
        "Period 5",
        "Period 6"
      ],
      ["1", 0, 0, 1, 1, 2, 2],
      ["2", 3, 4, 2, 0, 5, 1],
      ["3", 4, 4, 3, 3],
      ["4", 5, 5, 1, 1, 2, 0],
      ["5", 4, 3, 5, 5]
    ],
    "widths": [
      [7, 7, 7, 7, 7, 7, 7],
      [7, 7, 7, 7, 7, 7, 7],
      [7, 7, 7, 7, 7, 7, 7],
      [7, 7, 7, 7, 7, 7, 7],
      [7, 7, 7, 7, 7, 7, 7],
      [7, 7, 7, 7, 7, 7, 7],
      [7, 7, 7, 7, 7, 7, 7],
      [7, 7, 7, 7, 7, 7, 7],
      [7, 7, 7, 7, 7, 7, 7],
      [7, 7, 7, 7, 7, 7, 7],
      [7, 7, 7, 7, 7, 7, 7],
      [7, 7, 7, 7, 7, 7, 7]
    ]
  },
  {
    "name": "NCSS 2024",
    "classes": [
      ["Registration", "00f8"],
      ["Opening ceremony", "00f8"],
      ["Lecture", "ff08"],
      ["Dinner", "fff8"],
      ["Roll-call", "f008"],
      ["Group building activities", "00f8"],
      ["Breakfast", "fff8"],
      ["Tutorial", "0f08"],
      ["Lunch", "fff8"],
      ["Trivia", "00f8"],
      ["Free time", "fff8"],
      ["Scavenger hunt", "00f8"],
      ["Masterclasses", "00f8"],
      ["City excursion", "fff8"],
      ["Crypto", "00f8"],
      ["Site Visits", "00f8"],
      ["Offical Dinner", "00f8"]
    ],
    "rows": [
      [
        "Day",
        "8am",
        "9am",
        "10am",
        "11am",
        "12pm",
        "1pm",
        "2pm",
        "3pm",
        "4pm",
        "5pm",
        "6pm",
        "7pm",
        "8pm",
        "9pm"
      ],
      ["1", null, 0, 1, 2, 3, 4, 5],
      ["2", 6, 4, 2, 7, 8, 4, 2, 7, 3, 4, 9],
      ["3", 6, 4, 2, 7, 8, 4, 2, 7, 3, 4, 10],
      ["4", 6, 4, 2, 7, 8, 4, 2, 7, 3, 4, 11],
      ["5", 6, 4, 2, 12, 8, 4, 13, 4, 3, 4, 14],
      ["6", 4, 15, 10, 4, 16],
      ["7", 6, 4, 2, 7, 8, 4, 2, 7, 3, 4, 9],
      ["8", 6, 4, 2, 7, 8, 4, 2, 7, 3, 4, 9],
      ["9", 6, 4, 2, 7, 8, 4, 2, 7, 3, 4, 9],
      ["10", 6, 4, 2, 7, 8, 4, 2, 7, 3, 4, 9]
    ],
    "widths": [
      [15, 15, 15, 15, 15, 15, 15, 15, 15, 15, 15, 15, 15, 15, 15],
      [15, "(15/7)", 15, 15, 15, 20, 60, 5],
      [15, 20, 60, 15, "(15/2.75)", 15, 60, 15, 5, 20, 60, 5],
      [15, 20, 60, 15, "(15/2.75)", 15, 60, 15, 5, 20, 60, 5],
      [15, 20, 60, 15, "(15/2.75)", 15, 60, 15, 5, 20, 60, 5],
      [15, 20, 60, 15, "(15/2.75)", 15, 60, "(15/3.75)", 60, 20, 60, 5],
      [15, 60, "(15/8.25)", 12, 60, 5],
      [15, 20, 60, 15, "(15/2.75)", 15, 60, 15, 5, 20, 60, 5],
      [15, 20, 60, 15, "(15/2.75)", 15, 60, 15, 5, 20, 60, 5],
      [15, 20, 60, 15, "(15/2.75)", 15, 60, 15, 5, 20, 60, 5],
      [15, 20, 60, 15, "(15/2.75)", 15, 60, 15, 5, 20, 60, 5],
      [15, 20, 60, 15, "(15/2.75)", 15, 60, 15, 5, 20, 60, 5]
    ]
  }
]
